[
  {
    "id": 1,
    "title": "候補問題 No.1",
    "focus": "単相2線式・片切スイッチ",
    "singleLineImage": "/images/circuits/single-phase-2wire.svg",
    "steps": [
      "施工条件を確認し、器具配置とケーブルルートを先に決める。",
      "接地側（白）を負荷へ先に通し、分岐点を確定する。",
      "非接地側（黒）をスイッチ経由で負荷へ接続する。",
      "リングスリーブ/差込形コネクタを条件通りに施工する。",
      "極性・刻印・芯線露出を最終確認して完成。"
    ],
    "tip": "白線先行で組むと配線ミスを減らせます。"
  },
  {
    "id": 2,
    "title": "候補問題 No.2",
    "focus": "単相3線式・分岐回路",
    "singleLineImage": "/images/circuits/single-phase-3wire.svg",
    "steps": [
      "電源線の役割（白・黒・赤）を図面から読み取る。",
      "中性線（白）を各負荷へ均等に配線する。",
      "黒線/赤線の分岐先を器具ごとに接続する。",
      "圧着サイズと刻印を施工条件に合わせる。",
      "導通と極性を確認して完成。"
    ],
    "tip": "3線式は色と行き先の管理が最優先です。"
  },
  {
    "id": 3,
    "title": "候補問題 No.3",
    "focus": "3路スイッチ回路",
    "singleLineImage": "/images/circuits/3way-switch-circuit.svg",
    "steps": [
      "3路スイッチの共通端子を先に特定する。",
      "白線を負荷側へ先行配線する。",
      "渡り線2本をスイッチ間で確実に接続する。",
      "共通端子と負荷側の接続を確認する。",
      "点灯動作を想定して最終チェックする。"
    ],
    "tip": "3路は共通端子の取り違えが最大の失点要因です。"
  },
  {
    "id": 4,
    "title": "候補問題 No.4",
    "focus": "直列・並列混在回路",
    "singleLineImage": "/images/circuits/parallel-circuit.svg",
    "steps": [
      "負荷ごとの接続方式（直列/並列）を仕分ける。",
      "中性線を各負荷に正しく配線する。",
      "スイッチ側の非接地線を負荷へ割り当てる。",
      "分岐部の接続点を確定して圧着する。",
      "回路図と実配線を突き合わせて確認する。"
    ],
    "tip": "並列負荷は中性線の取り回しミスに注意します。"
  },
  {
    "id": 5,
    "title": "候補問題 No.5",
    "focus": "器具混在回路",
    "singleLineImage": "/images/circuits/single-to-multi.svg",
    "steps": [
      "器具ごとの端子極性と剥き代条件を確認する。",
      "白線を一筆書きで各器具へ接続する。",
      "黒線をスイッチ経由で必要器具へ配線する。",
      "差込形コネクタと圧着を使い分けて接続する。",
      "外観・緩み・芯線露出を確認して完成。"
    ],
    "tip": "器具の端子向きは施工前に揃えておくと速いです。"
  },
  {
    "id": 6,
    "title": "候補問題 No.6",
    "focus": "照明回路基礎",
    "singleLineImage": "/images/circuits/series-circuit.svg",
    "steps": [
      "負荷とスイッチの接続順を図面で確定する。",
      "接地側を負荷へ先行して配線する。",
      "非接地側をスイッチへ通して負荷へ戻す。",
      "接続部の圧着と被覆処理を行う。",
      "動作・極性・刻印を確認する。"
    ],
    "tip": "負荷への戻り線を先に想定してから施工します。"
  },
  {
    "id": 7,
    "title": "候補問題 No.7",
    "focus": "単相2線式応用",
    "singleLineImage": "/images/circuits/single-phase-2wire.svg",
    "steps": [
      "配線の分岐点を先にメモしてから作業開始する。",
      "白線系統を完了させる。",
      "黒線系統をスイッチ条件に合わせて接続する。",
      "結線部を圧着/コネクタで仕上げる。",
      "施工条件との一致を確認する。"
    ],
    "tip": "白線完了後に黒線を組むと見直しが速いです。"
  },
  {
    "id": 8,
    "title": "候補問題 No.8",
    "focus": "単相3線式応用",
    "singleLineImage": "/images/circuits/single-phase-3wire.svg",
    "steps": [
      "白・黒・赤の役割を明確に分離する。",
      "白線配線を先行して負荷へ通す。",
      "黒線/赤線を図面どおりに負荷へ割り当てる。",
      "分岐接続を施工条件どおりに圧着する。",
      "誤接続がないか全経路を目視確認する。"
    ],
    "tip": "色分けで迷ったら図面に戻るのが最短です。"
  },
  {
    "id": 9,
    "title": "候補問題 No.9",
    "focus": "スイッチ混在回路",
    "singleLineImage": "/images/circuits/3way-switch-circuit.svg",
    "steps": [
      "スイッチ種類ごとの端子仕様を確認する。",
      "白線を負荷側に先行配線する。",
      "スイッチ側黒線と渡り線を接続する。",
      "器具端子への締付と絶縁処理を行う。",
      "点灯想定で回路チェックを行う。"
    ],
    "tip": "端子番号の見間違いを最後に再確認します。"
  },
  {
    "id": 10,
    "title": "候補問題 No.10",
    "focus": "分岐回路実戦",
    "singleLineImage": "/images/circuits/parallel-circuit.svg",
    "steps": [
      "分岐先を器具単位で仕分ける。",
      "中性線を先に各負荷へ接続する。",
      "非接地線をスイッチ条件に合わせて配線する。",
      "圧着サイズと本数を照合して施工する。",
      "欠陥判定ポイントをチェックする。"
    ],
    "tip": "分岐点を見失わないよう配線前に整理します。"
  },
  {
    "id": 11,
    "title": "候補問題 No.11",
    "focus": "複線図展開",
    "singleLineImage": "/images/circuits/single-to-multi.svg",
    "steps": [
      "単線図を複線図へ書き換えてから施工する。",
      "白線系統を先に完成させる。",
      "黒線系統をスイッチ経由で構成する。",
      "結線部の圧着・コネクタ処理を行う。",
      "複線図どおりか最終照合する。"
    ],
    "tip": "複線図を先に決めると施工時間を短縮できます。"
  },
  {
    "id": 12,
    "title": "候補問題 No.12",
    "focus": "器具多め構成",
    "singleLineImage": "/images/circuits/series-circuit.svg",
    "steps": [
      "器具ごとの端子極性と配線条件を確認する。",
      "白線を共通系統として配線する。",
      "黒線を器具条件に合わせて接続する。",
      "施工条件に合う接続部材で仕上げる。",
      "外観欠陥の有無をチェックする。"
    ],
    "tip": "器具が多い問題は端子向きの統一が効果的です。"
  },
  {
    "id": 13,
    "title": "候補問題 No.13",
    "focus": "本番想定総合",
    "singleLineImage": "/images/circuits/single-phase-2wire.svg",
    "steps": [
      "施工条件を読み、40分の作業配分を決める。",
      "白線系統を先行して固定する。",
      "黒線系統をスイッチ条件に合わせる。",
      "圧着・絶縁・結線を順に仕上げる。",
      "最終確認チェックリストで採点する。"
    ],
    "tip": "本番では『配線→結線→確認』の順を崩さないこと。"
  }
]
